json_database/__init__.py
json_database/crypto.py
json_database/exceptions.py
json_database/hpm.py
json_database/search.py
json_database/utils.py
json_database/version.py
json_database/xdg_utils.py
json_database-0.10.1.dist-info/LICENSE
json_database-0.10.1.dist-info/METADATA
json_database-0.10.1.dist-info/WHEEL
json_database-0.10.1.dist-info/entry_points.txt
json_database-0.10.1.dist-info/top_level.txt
json_database-0.10.1.dist-info/RECORD
