Metadata-Version: 2.1
Name: json_database
Version: 0.10.1
Summary: searchable json database with persistence
Home-page: https://github.com/TigreGotico/json_database
Author: jarbasAI
Author-email: jarbasai@mailfence.com
License: MIT
Platform: UNKNOWN
